LICENSE
base2048/__init__.py
base2048/_b2048.py
base2048/b2048.data
base2048/py.typed
mikeshardmind_base2048-1.0.3.dist-info/METADATA
mikeshardmind_base2048-1.0.3.dist-info/WHEEL
mikeshardmind_base2048-1.0.3.dist-info/licenses/LICENSE
mikeshardmind_base2048-1.0.3.dist-info/RECORD
