Metadata-Version: 2.3
Name: mikeshardmind-base2048
Version: 1.0.3
Summary: Pure python Base-2048 binary-text encoding
Project-URL: Homepage, https://github.com/mikeshardmind/python-base2048
Author-email: Michael Hall <michael@michaelhall.tech>
License-Expression: MPL-2.0
License-File: LICENSE
Classifier: Development Status :: 5 - Production/Stable
Classifier: Intended Audience :: Developers
Classifier: Programming Language :: Python :: 3.9
Classifier: Programming Language :: Python :: 3.10
Classifier: Programming Language :: Python :: 3.11
Classifier: Programming Language :: Python :: 3.12
Classifier: Programming Language :: Python :: 3.13
Requires-Python: >=3.9
